pystassh/__init__.py
pystassh/api.py
pystassh/channel.py
pystassh/exceptions.py
pystassh/result.py
pystassh/session.py
tests/__init__.py
tests/test_api.py
tests/test_channel.py
tests/test_result.py
tests/test_session.py
pystassh-1.2.2.dist-info/LICENSE
pystassh-1.2.2.dist-info/METADATA
pystassh-1.2.2.dist-info/WHEEL
pystassh-1.2.2.dist-info/top_level.txt
pystassh-1.2.2.dist-info/RECORD
