Metadata-Version: 2.1
Name: pystassh
Version: 1.2.2
Summary: An easy to use libssh wrapper to execute commands on a remote server via SSH with Python
Home-page: https://julienc91.github.io/pystassh/
Author: Julien Chaumont
Author-email: pystassh@julienc.io
License: MIT
Platform: UNKNOWN
License-File: LICENSE
Requires-Dist: cffi
